maglev/__init__.py
maglev-0.0.1.post2.dist-info/WHEEL
maglev-0.0.1.post2.dist-info/METADATA
maglev-0.0.1.post2.dist-info/RECORD
