Metadata-Version: 2.1
Name: maglev
Version: 0.0.1.post2
Summary: Python utilities for working with NVIDIA's MLOps infrastructure.
License: Proprietary
Author: Eric Hall
Author-email: ehall@nvidia.com
Maintainer: Ryan Miller
Maintainer-email: rjmill@nvidia.com
Requires-Python: >=3.6,<4.0
Classifier: License :: Other/Proprietary License
Classifier: Programming Language :: Python :: 3
Classifier: Programming Language :: Python :: 3.6
Classifier: Programming Language :: Python :: 3.7
Classifier: Programming Language :: Python :: 3.8
Classifier: Programming Language :: Python :: 3.9
